python_presenter/__init__.py
python_presenter/core/__init__.py
python_presenter/core/presenters/__init__.py
python_presenter/core/presenters/base_presenter.py
python_presenter/core/presenters/presenter_helper.py
python_presenter/core/templatetags/__init__.py
python_presenter/core/templatetags/presenter_tag.py
python_presenter-0.1.0.dist-info/LICENSE
python_presenter-0.1.0.dist-info/METADATA
python_presenter-0.1.0.dist-info/WHEEL
python_presenter-0.1.0.dist-info/top_level.txt
python_presenter-0.1.0.dist-info/RECORD
