Metadata-Version: 2.1
Name: python-presenter
Version: 0.1.0
Summary: Presenter pattern to help manage the complexity of bloated controllers/views and logic-laden templates
Home-page: https://github.com/AfolabiOlaoluwa/python-presenter
Author: Olaoluwa Afolabi
Author-email: afolabiolaoluwa@gmail.com
Classifier: Development Status :: 5 - Production/Stable
Classifier: Programming Language :: Python :: 3.8
Classifier: License :: OSI Approved :: MIT License
Classifier: Operating System :: OS Independent
Classifier: Intended Audience :: Developers
Requires-Python: >=3.6
License-File: LICENSE
Requires-Dist: requests>=2.32
Requires-Dist: tenacity>=9.0.0
Provides-Extra: production
Provides-Extra: test
Requires-Dist: pytest; extra == "test"
Requires-Dist: pytest-env; extra == "test"
Requires-Dist: pytest-cov; extra == "test"
Requires-Dist: vcrpy; extra == "test"
Requires-Dist: requests-mock; extra == "test"
Provides-Extra: lint
Requires-Dist: flake8; extra == "lint"
Requires-Dist: flake8-docstrings; extra == "lint"
Requires-Dist: black; extra == "lint"
Requires-Dist: isort; extra == "lint"
Provides-Extra: docs
Requires-Dist: pytest; extra == "docs"
Requires-Dist: pytest-env; extra == "docs"
Requires-Dist: pytest-cov; extra == "docs"
Requires-Dist: vcrpy; extra == "docs"
Requires-Dist: requests-mock; extra == "docs"
Requires-Dist: flake8; extra == "docs"
Requires-Dist: flake8-docstrings; extra == "docs"
Requires-Dist: black; extra == "docs"
Requires-Dist: isort; extra == "docs"
Requires-Dist: ipdb; extra == "docs"
Provides-Extra: dev
Requires-Dist: pytest; extra == "dev"
Requires-Dist: pytest-env; extra == "dev"
Requires-Dist: pytest-cov; extra == "dev"
Requires-Dist: vcrpy; extra == "dev"
Requires-Dist: requests-mock; extra == "dev"
Requires-Dist: flake8; extra == "dev"
Requires-Dist: flake8-docstrings; extra == "dev"
Requires-Dist: black; extra == "dev"
Requires-Dist: isort; extra == "dev"
Requires-Dist: ipdb; extra == "dev"
Provides-Extra: deploy
Requires-Dist: requests; extra == "deploy"
Requires-Dist: twine; extra == "deploy"
